ppq/__init__.py
ppq/IR/__init__.py
ppq/IR/deploy.py
ppq/IR/morph.py
ppq/IR/processer.py
ppq/IR/quantize.py
ppq/IR/search.py
ppq/IR/training.py
ppq/IR/base/__init__.py
ppq/IR/base/command.py
ppq/IR/base/graph.py
ppq/IR/base/opdef.py
ppq/api/__init__.py
ppq/api/fsys.py
ppq/api/interface.py
ppq/api/setting.py
ppq/core/__init__.py
ppq/core/common.py
ppq/core/config.py
ppq/core/data.py
ppq/core/defs.py
ppq/core/ffi.py
ppq/core/quant.py
ppq/core/storage.py
ppq/csrc/export.cc
ppq/csrc/build/readme.md
ppq/csrc/cpu/common.h
ppq/csrc/cpu/hist_mse.cc
ppq/csrc/cpu/hist_mse.h
ppq/csrc/cuda/PPQ.h
ppq/csrc/cuda/common.cuh
ppq/csrc/cuda/common.h
ppq/csrc/cuda/floating.cu
ppq/csrc/cuda/floating.h
ppq/csrc/cuda/isotone.cc
ppq/csrc/cuda/isotone.h
ppq/csrc/cuda/linear.cu
ppq/csrc/cuda/linear.h
ppq/csrc/cuda/sort.cu
ppq/csrc/cuda/sort.h
ppq/csrc/cuda/test.cu
ppq/csrc/cuda/test.h
ppq/csrc/cuda/train.cu
ppq/csrc/cuda/train.h
ppq/executor/__init__.py
ppq/executor/base.py
ppq/executor/torch.py
ppq/executor/op/__init__.py
ppq/executor/op/torch/__init__.py
ppq/executor/op/torch/academic.py
ppq/executor/op/torch/base.py
ppq/executor/op/torch/cuda.py
ppq/executor/op/torch/default.py
ppq/executor/op/torch/dsp.py
ppq/executor/op/torch/extension.py
ppq/executor/op/torch/nxp.py
ppq/executor/op/torch/onnx.py
ppq/lib/__init__.py
ppq/lib/common.py
ppq/lib/extension.py
ppq/lib/quant.py
ppq/log/__init__.py
ppq/log/logger.py
ppq/parser/__init__.py
ppq/parser/ascend_export.py
ppq/parser/caffe_exporter.py
ppq/parser/caffe_parser.py
ppq/parser/extension.py
ppq/parser/mnn_exporter.py
ppq/parser/native.py
ppq/parser/ncnn_exporter.py
ppq/parser/nxp_exporter.py
ppq/parser/onnx_exporter.py
ppq/parser/onnx_parser.py
ppq/parser/onnxruntime_exporter.py
ppq/parser/openvino_exporter.py
ppq/parser/ppl.py
ppq/parser/qnn_exporter.py
ppq/parser/tengine_exporter.py
ppq/parser/tensorRT.py
ppq/parser/util.py
ppq/parser/caffe/__init__.py
ppq/parser/caffe/caffe.proto
ppq/parser/caffe/caffe_export_utils.py
ppq-0.6.6.dist-info/LICENSE
ppq-0.6.6.dist-info/METADATA
ppq-0.6.6.dist-info/WHEEL
ppq-0.6.6.dist-info/top_level.txt
ppq-0.6.6.dist-info/RECORD
