Metadata-Version: 2.1
Name: ppq
Version: 0.6.6
Summary: PPQ is an offline quantization tools
Home-page: UNKNOWN
Author: ppq
Author-email: dcp-ppq@sensetime.com
License: Apache License 2.0
Platform: UNKNOWN
Classifier: Development Status :: 3 - Alpha
Classifier: License :: OSI Approved :: Apache Software License
Classifier: Operating System :: OS Independent
Classifier: Programming Language :: Python :: 3.6
Classifier: Programming Language :: Python :: 3.7
Classifier: Programming Language :: Python :: 3.8
Classifier: Programming Language :: Python :: 3.9
Requires-Python: >=3.6
License-File: LICENSE
Requires-Dist: numpy
Requires-Dist: onnx (>=1.9.0)
Requires-Dist: protobuf
Requires-Dist: torch (>=1.6.0)
Requires-Dist: tqdm
